framework_python/__init__.py
framework_python/aws_client.py
framework_python/handler_decorator.py
framework_python-0.0.14.dist-info/METADATA
framework_python-0.0.14.dist-info/WHEEL
framework_python-0.0.14.dist-info/top_level.txt
framework_python-0.0.14.dist-info/RECORD
